setup.py
version.txt
entransit/__init__.py
entransit.common.egg-info/PKG-INFO
entransit.common.egg-info/SOURCES.txt
entransit.common.egg-info/dependency_links.txt
entransit.common.egg-info/namespace_packages.txt
entransit.common.egg-info/requires.txt
entransit.common.egg-info/top_level.txt
entransit/common/__init__.py
entransit/common/blob.py
entransit/common/client.py
entransit/common/exceptions.py
entransit/common/logger.py
entransit/common/path/__init__.py
