Metadata-Version: 1.0
Name: entransit.common
Version: 1.0.0
Summary: Common library shared between the entransit client and server
Home-page: http://enfoldsystems.com/Products/Entransit
Author: Sidnei da Silva
Author-email: sidnei@enfoldsystems.com
License: GNU General Public License (GPL)
Keywords: framework deployment
Platform: UNKNOWN
Classifier: Development Status :: 5 - Production/Stable
Classifier: Environment :: Web Environment
Classifier: License :: OSI Approved :: GNU General Public License (GPL)
Classifier: Operating System :: OS Independent
Classifier: Programming Language :: Python
Classifier: Topic :: Internet :: WWW/HTTP
Classifier: Topic :: Software Development :: Libraries :: Python Modules
